waterline/__init__.py
waterline/jobs.py
waterline/linker.py
waterline/pipeline.py
waterline/run.py
waterline/suite.py
waterline/utils.py
waterline/workspace.py
waterline/patches/Embench/support/main.c
waterline/patches/MiBench/automotive/basicmath/Makefile
waterline/patches/MiBench/automotive/basicmath/basicmath_large.c
waterline/patches/MiBench/automotive/basicmath/runme_basicmath.sh
waterline/patches/MiBench/automotive/bitcount/Makefile
waterline/patches/MiBench/automotive/bitcount/runme_bitcnts.sh
waterline/patches/MiBench/automotive/qsort/Makefile
waterline/patches/MiBench/automotive/qsort/input_verylarge.dat.xz
waterline/patches/MiBench/automotive/qsort/qsort_large.c
waterline/patches/MiBench/automotive/qsort/runme_qsort.sh
waterline/patches/MiBench/automotive/qsort/unpack_input.sh
waterline/patches/MiBench/automotive/susan/Makefile
waterline/patches/MiBench/automotive/susan/runme_susan_c.sh
waterline/patches/MiBench/automotive/susan/runme_susan_e.sh
waterline/patches/MiBench/automotive/susan/runme_susan_s.sh
waterline/patches/MiBench/automotive/susan/susan.c
waterline/patches/MiBench/consumer/jpeg/input_very_large.jpeg
waterline/patches/MiBench/consumer/jpeg/runme_cjpeg.sh
waterline/patches/MiBench/consumer/jpeg/runme_djpeg.sh
waterline/patches/MiBench/consumer/jpeg/unpack_input.sh
waterline/patches/MiBench/consumer/jpeg/jpeg-6a/Makefile
waterline/patches/MiBench/consumer/lame/runme_lame.sh
waterline/patches/MiBench/consumer/lame/unpack_input.sh
waterline/patches/MiBench/consumer/lame/lame3.70/Makefile
waterline/patches/MiBench/consumer/typeset/runme_lout.sh
waterline/patches/MiBench/consumer/typeset/lout-3.24/Makefile
waterline/patches/MiBench/network/dijkstra/Makefile
waterline/patches/MiBench/network/dijkstra/dijkstra_large.c
waterline/patches/MiBench/network/dijkstra/runme_dijkstra.sh
waterline/patches/MiBench/office/stringsearch/Makefile
waterline/patches/MiBench/office/stringsearch/pbmsrch_large.c
waterline-0.2.0.dist-info/LICENSE
waterline-0.2.0.dist-info/METADATA
waterline-0.2.0.dist-info/WHEEL
waterline-0.2.0.dist-info/top_level.txt
waterline-0.2.0.dist-info/RECORD
