Metadata-Version: 2.1
Name: waterline
Version: 0.2.0
Summary: A unified LLVM benchmark pipeliner
Author: Nick Wanninger
License: MIT
License-File: LICENSE
Requires-Dist: rich
Requires-Dist: requests
Requires-Dist: pandas
